README.md
setup.py
cmdroute/__init__.py
cmdroute/builtins.py
cmdroute/cmdroute.py
cmdroute/storage.py
cmdroute/utils.py
cmdroute.egg-info/PKG-INFO
cmdroute.egg-info/SOURCES.txt
cmdroute.egg-info/dependency_links.txt
cmdroute.egg-info/top_level.txt
test/__init__.py
test/cmdroute.py