Metadata-Version: 2.1
Name: cmdroute
Version: 0.0.3.1
Summary: pythonic cmd utility
Home-page: https://github.com/eaybek/cmdroute
Author: Erdem Aybek
Author-email: eaybek@gmail.com
License: UNKNOWN
Platform: UNKNOWN
Classifier: Programming Language :: Python :: 3
Classifier: License :: OSI Approved :: MIT License
Classifier: Operating System :: POSIX :: Linux
Classifier: Development Status :: 1 - Planning
Requires-Python: >=3.6
